text_utils/__init__.py
text_utils/utils.py
text_utils_tania/__init__.py
text_utils_tania_pypi-0.0.1.dist-info/METADATA
text_utils_tania_pypi-0.0.1.dist-info/WHEEL
text_utils_tania_pypi-0.0.1.dist-info/top_level.txt
text_utils_tania_pypi-0.0.1.dist-info/RECORD
