Metadata-Version: 2.4
Name: text-utils-tania-pypi
Version: 0.0.1
Summary: Funções simples para manipulação de texto
Home-page: https://github.com/seuusuario/text-utils
Author: tania.cremonini
Author-email: taninha_cremonini@hotmail.com
Requires-Python: >=3.6
Dynamic: author
Dynamic: author-email
Dynamic: description
Dynamic: description-content-type
Dynamic: home-page
Dynamic: requires-python
Dynamic: summary
